Metadata-Version: 1.0
Name: minervaboto
Version: 1.1.1
Summary: A renewal tool for Acervo Minerva
Home-page: https://github.com/erickpires/minervaboto
Author: Erick Pires
Author-email: rckkas@gmail.com
License: MIT
Platform: UNKNOWN
